{"name":"BooleanSupplier","comment":"Represents a supplier of {@code boolean}-valued results.  This is the\n {@code boolean}-producing primitive specialization of {@link Supplier}.\n\n \u003cp\u003eThere is no requirement that a new or distinct result be returned each\n time the supplier is invoked.\n\n \u003cp\u003eThis is a \u003ca href\u003d\"package-summary.html\"\u003efunctional interface\u003c/a\u003e\n whose functional method is {@link #getAsBoolean()}.","isClass":false,"isInterface":true,"isEnum":false,"isEnumConstant":false,"isConstructor":false,"isField":false,"isMethod":false,"isOrdinaryClass":false,"isPrimitive":false,"simpleName":"BooleanSupplier","qualifiedName":"java.util.function.BooleanSupplier","dimension":"","elementType":{},"package":"java.util.function","interfaces":[],"isAbstract":true,"isStatic":false,"since":"1.8","innerClasses":[],"isInnerClass":false,"constructors":[],"fields":[],"methods":[{"name":"getAsBoolean","comment":"Gets a result.","isClass":false,"isInterface":false,"isEnum":false,"isEnumConstant":false,"isConstructor":false,"isField":false,"isMethod":true,"isOrdinaryClass":false,"signature":"()","flatSignature":"()","returnType":{"isPrimitive":true,"simpleName":"boolean","qualifiedName":"boolean","dimension":"","elementType":{}},"isAbstract":true,"isDefault":false,"isStatic":false,"parameters":[],"typeParameters":[]}],"typeParameters":[],"enumConstants":[]}