{"name":"ECGenParameterSpec","comment":"This immutable class specifies the set of parameters used for\n generating elliptic curve (EC) domain parameters.","isClass":true,"isInterface":false,"isEnum":false,"isEnumConstant":false,"isConstructor":false,"isField":false,"isMethod":false,"isOrdinaryClass":true,"isPrimitive":false,"simpleName":"ECGenParameterSpec","qualifiedName":"java.security.spec.ECGenParameterSpec","dimension":"","elementType":{},"package":"java.security.spec","superclass":"java.lang.Object","interfaces":["java.security.spec.AlgorithmParameterSpec"],"isAbstract":false,"isStatic":false,"since":"1.5","innerClasses":[],"isInnerClass":false,"constructors":[{"name":"ECGenParameterSpec","comment":"Creates a parameter specification for EC parameter\n generation using a standard (or predefined) name\n {@code stdName} in order to generate the corresponding\n (precomputed) elliptic curve domain parameters. For the\n list of supported names, please consult the documentation\n of provider whose implementation will be used.","isClass":false,"isInterface":false,"isEnum":false,"isEnumConstant":false,"isConstructor":true,"isField":false,"isMethod":false,"isOrdinaryClass":false,"signature":"(java.lang.String)","flatSignature":"(String)","parameters":[{"name":"stdName","type":{"isPrimitive":false,"simpleName":"String","qualifiedName":"java.lang.String","dimension":"","elementType":{}}}],"typeParameters":[]}],"fields":[],"methods":[{"name":"getName","comment":"Returns the standard or predefined name of the\n to-be-generated EC domain parameters.","isClass":false,"isInterface":false,"isEnum":false,"isEnumConstant":false,"isConstructor":false,"isField":false,"isMethod":true,"isOrdinaryClass":false,"signature":"()","flatSignature":"()","returnType":{"isPrimitive":false,"simpleName":"String","qualifiedName":"java.lang.String","dimension":"","elementType":{}},"isAbstract":false,"isDefault":false,"isStatic":false,"parameters":[],"typeParameters":[]}],"typeParameters":[],"enumConstants":[]}