{"name":"BreakIteratorProvider","comment":"An abstract class for service providers that\n provide concrete implementations of the\n {@link java.text.BreakIterator BreakIterator} class.","isClass":true,"isInterface":false,"isEnum":false,"isEnumConstant":false,"isConstructor":false,"isField":false,"isMethod":false,"isOrdinaryClass":true,"isPrimitive":false,"simpleName":"BreakIteratorProvider","qualifiedName":"java.text.spi.BreakIteratorProvider","dimension":"","elementType":{},"package":"java.text.spi","superclass":"java.util.spi.LocaleServiceProvider","interfaces":[],"isAbstract":true,"isStatic":false,"since":"1.6","innerClasses":[],"isInnerClass":false,"constructors":[],"fields":[],"methods":[{"name":"getWordInstance","comment":"Returns a new \u003ccode\u003eBreakIterator\u003c/code\u003e instance\n for \u003ca href\u003d\"../BreakIterator.html#word\"\u003eword breaks\u003c/a\u003e\n for the given locale.","isClass":false,"isInterface":false,"isEnum":false,"isEnumConstant":false,"isConstructor":false,"isField":false,"isMethod":true,"isOrdinaryClass":false,"signature":"(java.util.Locale)","flatSignature":"(Locale)","returnType":{"isPrimitive":false,"simpleName":"BreakIterator","qualifiedName":"java.text.BreakIterator","dimension":"","elementType":{}},"isAbstract":true,"isDefault":false,"isStatic":false,"parameters":[{"name":"locale","type":{"isPrimitive":false,"simpleName":"Locale","qualifiedName":"java.util.Locale","dimension":"","elementType":{}}}],"typeParameters":[]},{"name":"getLineInstance","comment":"Returns a new \u003ccode\u003eBreakIterator\u003c/code\u003e instance\n for \u003ca href\u003d\"../BreakIterator.html#line\"\u003eline breaks\u003c/a\u003e\n for the given locale.","isClass":false,"isInterface":false,"isEnum":false,"isEnumConstant":false,"isConstructor":false,"isField":false,"isMethod":true,"isOrdinaryClass":false,"signature":"(java.util.Locale)","flatSignature":"(Locale)","returnType":{"isPrimitive":false,"simpleName":"BreakIterator","qualifiedName":"java.text.BreakIterator","dimension":"","elementType":{}},"isAbstract":true,"isDefault":false,"isStatic":false,"parameters":[{"name":"locale","type":{"isPrimitive":false,"simpleName":"Locale","qualifiedName":"java.util.Locale","dimension":"","elementType":{}}}],"typeParameters":[]},{"name":"getCharacterInstance","comment":"Returns a new \u003ccode\u003eBreakIterator\u003c/code\u003e instance\n for \u003ca href\u003d\"../BreakIterator.html#character\"\u003echaracter breaks\u003c/a\u003e\n for the given locale.","isClass":false,"isInterface":false,"isEnum":false,"isEnumConstant":false,"isConstructor":false,"isField":false,"isMethod":true,"isOrdinaryClass":false,"signature":"(java.util.Locale)","flatSignature":"(Locale)","returnType":{"isPrimitive":false,"simpleName":"BreakIterator","qualifiedName":"java.text.BreakIterator","dimension":"","elementType":{}},"isAbstract":true,"isDefault":false,"isStatic":false,"parameters":[{"name":"locale","type":{"isPrimitive":false,"simpleName":"Locale","qualifiedName":"java.util.Locale","dimension":"","elementType":{}}}],"typeParameters":[]},{"name":"getSentenceInstance","comment":"Returns a new \u003ccode\u003eBreakIterator\u003c/code\u003e instance\n for \u003ca href\u003d\"../BreakIterator.html#sentence\"\u003esentence breaks\u003c/a\u003e\n for the given locale.","isClass":false,"isInterface":false,"isEnum":false,"isEnumConstant":false,"isConstructor":false,"isField":false,"isMethod":true,"isOrdinaryClass":false,"signature":"(java.util.Locale)","flatSignature":"(Locale)","returnType":{"isPrimitive":false,"simpleName":"BreakIterator","qualifiedName":"java.text.BreakIterator","dimension":"","elementType":{}},"isAbstract":true,"isDefault":false,"isStatic":false,"parameters":[{"name":"locale","type":{"isPrimitive":false,"simpleName":"Locale","qualifiedName":"java.util.Locale","dimension":"","elementType":{}}}],"typeParameters":[]}],"typeParameters":[],"enumConstants":[]}