{"name":"AsynchronousChannel","isClass":false,"isInterface":true,"isEnum":false,"isEnumConstant":false,"isConstructor":false,"isField":false,"isMethod":false,"isOrdinaryClass":false,"isPrimitive":false,"simpleName":"AsynchronousChannel","qualifiedName":"java.nio.channels.AsynchronousChannel","dimension":"","elementType":{},"package":"java.nio.channels","interfaces":["java.nio.channels.Channel"],"isAbstract":true,"isStatic":false,"since":"1.7","innerClasses":[],"isInnerClass":false,"constructors":[],"fields":[],"methods":[{"name":"close","isClass":false,"isInterface":false,"isEnum":false,"isEnumConstant":false,"isConstructor":false,"isField":false,"isMethod":true,"isOrdinaryClass":false,"signature":"()","flatSignature":"()","returnType":{"isPrimitive":true,"simpleName":"void","qualifiedName":"void","dimension":"","elementType":{}},"isAbstract":true,"isDefault":false,"isStatic":false,"parameters":[],"typeParameters":[]}],"typeParameters":[],"subInterfaces":["java.nio.channels.AsynchronousByteChannel","java.nio.channels.AsynchronousServerSocketChannel","java.nio.channels.AsynchronousFileChannel"],"enumConstants":[]}