{"name":"Closeable","comment":"A {@code Closeable} is a source or destination of data that can be closed.\n The close method is invoked to release resources that the object is\n holding (such as open files).","isClass":false,"isInterface":true,"isEnum":false,"isEnumConstant":false,"isConstructor":false,"isField":false,"isMethod":false,"isOrdinaryClass":false,"isPrimitive":false,"simpleName":"Closeable","qualifiedName":"java.io.Closeable","dimension":"","elementType":{},"package":"java.io","interfaces":["java.lang.AutoCloseable"],"isAbstract":true,"isStatic":false,"since":"1.5","innerClasses":[],"isInnerClass":false,"constructors":[],"fields":[],"methods":[{"name":"close","comment":"Closes this stream and releases any system resources associated\n with it. If the stream is already closed then invoking this\n method has no effect.\n\n \u003cp\u003e As noted in {@link AutoCloseable#close()}, cases where the\n close may fail require careful attention. It is strongly advised\n to relinquish the underlying resources and to internally\n \u003cem\u003emark\u003c/em\u003e the {@code Closeable} as closed, prior to throwing\n the {@code IOException}.","isClass":false,"isInterface":false,"isEnum":false,"isEnumConstant":false,"isConstructor":false,"isField":false,"isMethod":true,"isOrdinaryClass":false,"signature":"()","flatSignature":"()","returnType":{"isPrimitive":true,"simpleName":"void","qualifiedName":"void","dimension":"","elementType":{}},"isAbstract":true,"isDefault":false,"isStatic":false,"parameters":[],"typeParameters":[]}],"typeParameters":[],"subInterfaces":["java.net.URLClassLoader","java.net.Socket","java.net.ServerSocket","java.net.DatagramSocket","java.nio.channels.Channel","java.nio.channels.Selector","java.nio.file.WatchService","java.nio.file.DirectoryStream","java.nio.file.FileSystem","java.io.Writer","java.io.Reader","java.io.RandomAccessFile","java.io.PrintStream","java.io.OutputStream","java.io.InputStream","java.util.zip.ZipFile","java.util.Scanner","java.util.Formatter"],"enumConstants":[]}