{"name":"Serializable","isClass":false,"isInterface":true,"isEnum":false,"isEnumConstant":false,"isConstructor":false,"isField":false,"isMethod":false,"isOrdinaryClass":false,"isPrimitive":false,"simpleName":"Serializable","qualifiedName":"java.io.Serializable","dimension":"","elementType":{},"package":"java.io","interfaces":[],"isAbstract":true,"isStatic":false,"since":"JDK1.1","innerClasses":[],"isInnerClass":false,"constructors":[],"fields":[],"methods":[],"typeParameters":[],"enumConstants":[]}