{"name":"ContentHandlerFactory","comment":"This interface defines a factory for content handlers. An\n implementation of this interface should map a MIME type into an\n instance of {@code ContentHandler}.\n \u003cp\u003e\n This interface is used by the {@code URLStreamHandler} class\n to create a {@code ContentHandler} for a MIME type.","isClass":false,"isInterface":true,"isEnum":false,"isEnumConstant":false,"isConstructor":false,"isField":false,"isMethod":false,"isOrdinaryClass":false,"isPrimitive":false,"simpleName":"ContentHandlerFactory","qualifiedName":"java.net.ContentHandlerFactory","dimension":"","elementType":{},"package":"java.net","interfaces":[],"isAbstract":true,"isStatic":false,"since":"JDK1.0","innerClasses":[],"isInnerClass":false,"constructors":[],"fields":[],"methods":[{"name":"createContentHandler","comment":"Creates a new {@code ContentHandler} to read an object from\n a {@code URLStreamHandler}.","isClass":false,"isInterface":false,"isEnum":false,"isEnumConstant":false,"isConstructor":false,"isField":false,"isMethod":true,"isOrdinaryClass":false,"signature":"(java.lang.String)","flatSignature":"(String)","returnType":{"isPrimitive":false,"simpleName":"ContentHandler","qualifiedName":"java.net.ContentHandler","dimension":"","elementType":{}},"isAbstract":true,"isDefault":false,"isStatic":false,"parameters":[{"name":"mimetype","type":{"isPrimitive":false,"simpleName":"String","qualifiedName":"java.lang.String","dimension":"","elementType":{}}}],"typeParameters":[]}],"typeParameters":[],"enumConstants":[]}